setup.py
teby_probability/Binomialdistribution.py
teby_probability/Gaussiandistribution.py
teby_probability/Generaldistribution.py
teby_probability/__init__.py
teby_probability.egg-info/PKG-INFO
teby_probability.egg-info/SOURCES.txt
teby_probability.egg-info/dependency_links.txt
teby_probability.egg-info/not-zip-safe
teby_probability.egg-info/top_level.txt