Metadata-Version: 1.0
Name: teby-probability
Version: 1.0
Summary: Gaussian and Binomial distributions
Home-page: UNKNOWN
Author: Motebang Lebusa
Author-email: lebusam@gmail.com
License: UNKNOWN
Platform: UNKNOWN
